opyratorfront/__init__.py
opyratorfront/py2pydantic.py
opyratorfront-0.0.2.dist-info/LICENSE
opyratorfront-0.0.2.dist-info/METADATA
opyratorfront-0.0.2.dist-info/WHEEL
opyratorfront-0.0.2.dist-info/top_level.txt
opyratorfront-0.0.2.dist-info/RECORD
