Metadata-Version: 2.1
Name: opyratorfront
Version: 0.0.2
Summary: Generate opyrator UIs and webservices and docker containers from python functions
Home-page: https://github.com/i2mint/opyratorfront
Author: OtoSense
License: apache-2.0
Platform: any
License-File: LICENSE
